Metadata-Version: 2.1
Name: ibmsupervisor
Version: 0.25
Summary: Extract the supervisor password from the ROM dump of an IBM ThinkPad
Home-page: https://gitlab.com/eloydegen/ibmsupervisor
Author: Eloy
Author-email: degeneloy@gmail.com
License: MIT License
Classifier: Programming Language :: Python :: 3
License-File: LICENSE
